vp/__init__.py
vp-0.0.1.dist-info/METADATA
vp-0.0.1.dist-info/RECORD
vp-0.0.1.dist-info/WHEEL
vp-0.0.1.dist-info/top_level.txt
