Metadata-Version: 2.1
Name: vp
Version: 0.0.1
Summary: Markup Text Editor
Home-page: UNKNOWN
Author: prasad
Author-email: prasad.venkatesh@gmail.com
License: UNKNOWN
Platform: UNKNOWN
Classifier: Programming Language :: Python :: 3
Classifier: License :: OSI Approved :: MIT License
Classifier: Operating System :: OS Independent
